locate_pixelcolor_cythonsingle/LICENSE
locate_pixelcolor_cythonsingle/README.md
locate_pixelcolor_cythonsingle/__init__.py
locate_pixelcolor_cythonsingle/colorsearchcythonsingle.cp310-win_amd64.pyd
locate_pixelcolor_cythonsingle/colorsearchcythonsingle.pyx
locate_pixelcolor_cythonsingle/colorsearchcythonsinglesetup.py
locate_pixelcolor_cythonsingle/requirements.txt
locate_pixelcolor_cythonsingle/thirdparty.json
locate_pixelcolor_cythonsingle-0.11.dist-info/LICENSE.rst
locate_pixelcolor_cythonsingle-0.11.dist-info/METADATA
locate_pixelcolor_cythonsingle-0.11.dist-info/WHEEL
locate_pixelcolor_cythonsingle-0.11.dist-info/top_level.txt
locate_pixelcolor_cythonsingle-0.11.dist-info/RECORD
